nf_python/__init__.py
nf_python/nextflow.py
nf_python_plugin-0.1.2.dist-info/licenses/COPYING
nf_python_plugin-0.1.2.dist-info/METADATA
nf_python_plugin-0.1.2.dist-info/WHEEL
nf_python_plugin-0.1.2.dist-info/top_level.txt
nf_python_plugin-0.1.2.dist-info/RECORD
